{
  "main": [
    [
      "Update Time",
      "Symbol",
      "Imbalance",
      "Paired",
      "ADV",
      "% ImbADV"
    ],
    [
      "13:45:59",
      "SPGI",
      120000,
      20000,
      "1490000",
      "9"
    ],
    [
      "13:29:17",
      "XOM",
      70000,
      70000,
      "17560000",
      "1"
    ],
    [
      "13:29:06",
      "C",
      560000,
      160000,
      "17260000",
      "4"
    ],
    [
      "13:29:00",
      "ORCL",
      210000,
      50000,
      "10360000",
      "3"
    ],
    [
      "13:28:50",
      "JPM",
      140000,
      95000,
      "11510000",
      "2"
    ],
    [
      "13:28:44",
      "LLY",
      160000,
      65000,
      "3890000",
      "5"
    ],
    [
      "13:28:31",
      "ABBV",
      120000,
      100000,
      "7650000",
      "2"
    ],
    [
      "13:27:59",
      "VZ",
      380000,
      160000,
      "24450000",
      "2"
    ],
    [
      "13:27:51",
      "BA",
      150000,
      40000,
      "8940000",
      "2"
    ],
    [
      "13:27:21",
      "ACN",
      50000,
      40000,
      "3570000",
      "2"
    ],
    [
      "13:27:09",
      "RTX",
      110000,
      20000,
      "5600000",
      "2"
    ]
  ],
  "archive": {
    "SPGI": [
      [
        "Update Time",
        "Side",
        "Imbalance",
        "Paired"
      ],
      [
        "13:45:59",
        "BUY",
        120000,
        20000
      ],
      [
        "13:45:59",
        "BUY",
        120000,
        20000
      ]
    ],
    "XOM": [
      [
        "Update Time",
        "Side",
        "Imbalance",
        "Paired"
      ],
      [
        "13:29:17",
        "BUY",
        70000,
        70000
      ],
      [
        "13:29:17",
        "BUY",
        70000,
        70000
      ]
    ],
    "C": [
      [
        "Update Time",
        "Side",
        "Imbalance",
        "Paired"
      ],
      [
        "13:29:06",
        "BUY",
        560000,
        160000
      ],
      [
        "13:29:06",
        "BUY",
        560000,
        160000
      ]
    ],
    "ORCL": [
      [
        "Update Time",
        "Side",
        "Imbalance",
        "Paired"
      ],
      [
        "13:29:00",
        "BUY",
        210000,
        50000
      ],
      [
        "13:29:00",
        "BUY",
        210000,
        50000
      ]
    ],
    "JPM": [
      [
        "Update Time",
        "Side",
        "Imbalance",
        "Paired"
      ],
      [
        "13:28:50",
        "BUY",
        140000,
        95000
      ],
      [
        "13:28:50",
        "BUY",
        140000,
        95000
      ]
    ],
    "LLY": [
      [
        "Update Time",
        "Side",
        "Imbalance",
        "Paired"
      ],
      [
        "13:28:44",
        "BUY",
        160000,
        65000
      ],
      [
        "13:28:44",
        "BUY",
        160000,
        65000
      ]
    ],
    "ABBV": [
      [
        "Update Time",
        "Side",
        "Imbalance",
        "Paired"
      ],
      [
        "13:28:31",
        "BUY",
        120000,
        100000
      ],
      [
        "13:28:31",
        "BUY",
        120000,
        100000
      ]
    ],
    "VZ": [
      [
        "Update Time",
        "Side",
        "Imbalance",
        "Paired"
      ],
      [
        "13:27:59",
        "BUY",
        380000,
        160000
      ],
      [
        "13:27:59",
        "BUY",
        380000,
        160000
      ]
    ],
    "BA": [
      [
        "Update Time",
        "Side",
        "Imbalance",
        "Paired"
      ],
      [
        "13:27:51",
        "BUY",
        150000,
        40000
      ],
      [
        "13:27:51",
        "BUY",
        150000,
        40000
      ]
    ],
    "ACN": [
      [
        "Update Time",
        "Side",
        "Imbalance",
        "Paired"
      ],
      [
        "13:27:21",
        "BUY",
        50000,
        40000
      ],
      [
        "13:27:21",
        "BUY",
        50000,
        40000
      ]
    ],
    "RTX": [
      [
        "Update Time",
        "Side",
        "Imbalance",
        "Paired"
      ],
      [
        "13:27:09",
        "BUY",
        110000,
        20000
      ],
      [
        "13:27:09",
        "BUY",
        110000,
        20000
      ]
    ]
  }
}