{
  "main": [
    [
      "Update Time",
      "Symbol",
      "Imbalance",
      "Paired",
      "ADV",
      "% ImbADV"
    ],
    [
      "13:33:59",
      "V",
      55000,
      25000,
      "6500000",
      "1"
    ],
    [
      "13:33:44",
      "SCHW",
      100000,
      25000,
      "8750000",
      "2"
    ],
    [
      "13:33:31",
      "UBER",
      100000,
      110000,
      "17830000",
      "1"
    ],
    [
      "13:33:09",
      "NKE",
      170000,
      250000,
      "14610000",
      "2"
    ],
    [
      "13:33:00",
      "PM",
      120000,
      20000,
      "5780000",
      "3"
    ],
    [
      "13:32:40",
      "PFE",
      500000,
      100000,
      "40810000",
      "2"
    ],
    [
      "13:32:21",
      "MRK",
      130000,
      120000,
      "13800000",
      "1"
    ],
    [
      "13:32:13",
      "MS",
      50000,
      30000,
      "5210000",
      "1"
    ],
    [
      "13:31:49",
      "LOW",
      60000,
      10000,
      "2850000",
      "3"
    ],
    [
      "13:31:43",
      "JPM",
      230000,
      40000,
      "8340000",
      "3"
    ],
    [
      "13:31:21",
      "T",
      220000,
      120000,
      "31300000",
      "1"
    ],
    [
      "13:30:54",
      "UNP",
      100000,
      10000,
      "4170000",
      "3"
    ],
    [
      "13:30:46",
      "CAT",
      80000,
      10000,
      "2770000",
      "3"
    ],
    [
      "13:30:38",
      "BMY",
      100000,
      230000,
      "12420000",
      "1"
    ],
    [
      "13:30:24",
      "COP",
      70000,
      90000,
      "7160000",
      "1"
    ],
    [
      "13:30:12",
      "NEE",
      480000,
      100000,
      "10350000",
      "5"
    ]
  ],
  "archive": {
    "V": [
      [
        "Update Time",
        "Side",
        "Imbalance",
        "Paired"
      ],
      [
        "13:33:59",
        "BUY",
        55000,
        25000
      ]
    ],
    "SCHW": [
      [
        "Update Time",
        "Side",
        "Imbalance",
        "Paired"
      ],
      [
        "13:33:44",
        "BUY",
        100000,
        25000
      ]
    ],
    "UBER": [
      [
        "Update Time",
        "Side",
        "Imbalance",
        "Paired"
      ],
      [
        "13:33:31",
        "BUY",
        100000,
        110000
      ]
    ],
    "NKE": [
      [
        "Update Time",
        "Side",
        "Imbalance",
        "Paired"
      ],
      [
        "13:33:09",
        "BUY",
        170000,
        250000
      ]
    ],
    "PM": [
      [
        "Update Time",
        "Side",
        "Imbalance",
        "Paired"
      ],
      [
        "13:33:00",
        "BUY",
        120000,
        20000
      ]
    ],
    "PFE": [
      [
        "Update Time",
        "Side",
        "Imbalance",
        "Paired"
      ],
      [
        "13:32:40",
        "BUY",
        500000,
        100000
      ]
    ],
    "MRK": [
      [
        "Update Time",
        "Side",
        "Imbalance",
        "Paired"
      ],
      [
        "13:32:21",
        "BUY",
        130000,
        120000
      ]
    ],
    "MS": [
      [
        "Update Time",
        "Side",
        "Imbalance",
        "Paired"
      ],
      [
        "13:32:13",
        "BUY",
        50000,
        30000
      ]
    ],
    "LOW": [
      [
        "Update Time",
        "Side",
        "Imbalance",
        "Paired"
      ],
      [
        "13:31:49",
        "BUY",
        60000,
        10000
      ]
    ],
    "JPM": [
      [
        "Update Time",
        "Side",
        "Imbalance",
        "Paired"
      ],
      [
        "13:31:43",
        "BUY",
        230000,
        40000
      ]
    ],
    "T": [
      [
        "Update Time",
        "Side",
        "Imbalance",
        "Paired"
      ],
      [
        "13:31:21",
        "BUY",
        220000,
        120000
      ]
    ],
    "UNP": [
      [
        "Update Time",
        "Side",
        "Imbalance",
        "Paired"
      ],
      [
        "13:30:54",
        "BUY",
        100000,
        10000
      ]
    ],
    "CAT": [
      [
        "Update Time",
        "Side",
        "Imbalance",
        "Paired"
      ],
      [
        "13:30:46",
        "BUY",
        80000,
        10000
      ]
    ],
    "BMY": [
      [
        "Update Time",
        "Side",
        "Imbalance",
        "Paired"
      ],
      [
        "13:30:38",
        "BUY",
        100000,
        230000
      ]
    ],
    "COP": [
      [
        "Update Time",
        "Side",
        "Imbalance",
        "Paired"
      ],
      [
        "13:30:24",
        "BUY",
        70000,
        90000
      ]
    ],
    "NEE": [
      [
        "Update Time",
        "Side",
        "Imbalance",
        "Paired"
      ],
      [
        "13:30:12",
        "BUY",
        480000,
        100000
      ]
    ]
  }
}