{
  "main": [
    [
      "Update Time",
      "Symbol",
      "Imbalance",
      "Paired",
      "ADV",
      "% ImbADV"
    ],
    [
      "13:47:43",
      "UNH",
      190000,
      390000,
      "14320000",
      "2"
    ],
    [
      "13:47:38",
      "NKE",
      380000,
      720000,
      "19970000",
      "2"
    ],
    [
      "13:47:33",
      "MCD",
      60000,
      90000,
      "3660000",
      "2"
    ],
    [
      "13:47:29",
      "KO",
      5700000,
      1700000,
      "17880000",
      "32"
    ],
    [
      "13:47:24",
      "JNJ",
      750000,
      590000,
      "9390000",
      "8"
    ],
    [
      "13:47:20",
      "UBER",
      1400000,
      879000,
      "20940000",
      "7"
    ],
    [
      "13:47:12",
      "BAC",
      4000000,
      6400000,
      "49230000",
      "9"
    ],
    [
      "13:47:05",
      "SCHW",
      790000,
      500000,
      "10320000",
      "8"
    ],
    [
      "13:47:01",
      "MA",
      320000,
      330000,
      "2880000",
      "12"
    ],
    [
      "13:46:54",
      "IBM",
      320000,
      350000,
      "4680000",
      "7"
    ],
    [
      "13:46:41",
      "NEE",
      430000,
      470000,
      "13400000",
      "4"
    ],
    [
      "13:46:25",
      "GE",
      560000,
      480000,
      "6150000",
      "10"
    ],
    [
      "13:46:18",
      "CAT",
      60000,
      150000,
      "2930000",
      "3"
    ],
    [
      "13:45:30",
      "PFE",
      5900000,
      4600000,
      "53760000",
      "11"
    ],
    [
      "13:43:37",
      "RTX",
      260000,
      330000,
      "5530000",
      "5"
    ],
    [
      "13:43:21",
      "TMO",
      75000,
      110000,
      "2510000",
      "3"
    ],
    [
      "13:43:17",
      "BMY",
      780000,
      680000,
      "14760000",
      "6"
    ],
    [
      "13:43:10",
      "USB",
      850000,
      1100000,
      "11530000",
      "8"
    ],
    [
      "13:43:05",
      "HD",
      100000,
      100000,
      "3740000",
      "3"
    ],
    [
      "13:42:59",
      "COP",
      1000000,
      300000,
      "9410000",
      "11"
    ],
    [
      "13:29:57",
      "AXP",
      150000,
      50000,
      "3450000",
      "5"
    ],
    [
      "13:29:48",
      "C",
      500000,
      500000,
      "17170000",
      "3"
    ],
    [
      "13:29:28",
      "CVX",
      750000,
      0,
      "9780000",
      "8"
    ],
    [
      "13:29:13",
      "T",
      100000,
      0,
      "40850000",
      "1"
    ],
    [
      "13:29:00",
      "DHR",
      270000,
      330000,
      "4340000",
      "7"
    ],
    [
      "13:28:57",
      "ABBV",
      120000,
      820000,
      "7950000",
      "2"
    ],
    [
      "13:28:53",
      "UPS",
      75000,
      350000,
      "6220000",
      "2"
    ],
    [
      "13:28:48",
      "LOW",
      100000,
      150000,
      "2790000",
      "4"
    ],
    [
      "13:28:44",
      "ABT",
      200000,
      1200000,
      "7200000",
      "3"
    ],
    [
      "13:28:36",
      "MRK",
      250000,
      1200000,
      "16480000",
      "2"
    ],
    [
      "13:28:31",
      "PG",
      360000,
      1000000,
      "8600000",
      "5"
    ],
    [
      "13:27:49",
      "BA",
      200000,
      90000,
      "9440000",
      "3"
    ],
    [
      "13:27:44",
      "PM",
      200000,
      430000,
      "6610000",
      "4"
    ],
    [
      "13:26:45",
      "GS",
      80000,
      110000,
      "2970000",
      "3"
    ],
    [
      "13:26:41",
      "SPGI",
      50000,
      160000,
      "1390000",
      "4"
    ],
    [
      "13:26:08",
      "PLD",
      60000,
      370000,
      "5300000",
      "2"
    ],
    [
      "13:25:57",
      "DKL",
      70000,
      50000,
      "204320",
      "35"
    ],
    [
      "13:25:52",
      "FI",
      200000,
      800000,
      "4450000",
      "5"
    ]
  ],
  "archive": {
    "UNH": [
      [
        "Update Time",
        "Side",
        "Imbalance",
        "Paired"
      ],
      [
        "13:47:43",
        "BUY",
        190000,
        390000
      ],
      [
        "13:47:43",
        "BUY",
        190000,
        390000
      ]
    ],
    "NKE": [
      [
        "Update Time",
        "Side",
        "Imbalance",
        "Paired"
      ],
      [
        "13:47:38",
        "BUY",
        380000,
        720000
      ],
      [
        "13:47:38",
        "BUY",
        380000,
        720000
      ],
      [
        "13:27:31",
        "BUY",
        400000,
        600000
      ]
    ],
    "MCD": [
      [
        "Update Time",
        "Side",
        "Imbalance",
        "Paired"
      ],
      [
        "13:47:33",
        "BUY",
        60000,
        90000
      ],
      [
        "13:47:33",
        "BUY",
        60000,
        90000
      ]
    ],
    "KO": [
      [
        "Update Time",
        "Side",
        "Imbalance",
        "Paired"
      ],
      [
        "13:47:29",
        "BUY",
        5700000,
        1700000
      ],
      [
        "13:47:29",
        "BUY",
        5700000,
        1700000
      ],
      [
        "13:27:19",
        "BUY",
        1200000,
        1500000
      ]
    ],
    "JNJ": [
      [
        "Update Time",
        "Side",
        "Imbalance",
        "Paired"
      ],
      [
        "13:47:24",
        "BUY",
        750000,
        590000
      ],
      [
        "13:47:24",
        "BUY",
        750000,
        590000
      ],
      [
        "13:27:13",
        "BUY",
        380000,
        460000
      ]
    ],
    "UBER": [
      [
        "Update Time",
        "Side",
        "Imbalance",
        "Paired"
      ],
      [
        "13:47:20",
        "BUY",
        1400000,
        879000
      ],
      [
        "13:47:20",
        "BUY",
        1400000,
        879000
      ],
      [
        "13:27:09",
        "BUY",
        760000,
        780000
      ]
    ],
    "BAC": [
      [
        "Update Time",
        "Side",
        "Imbalance",
        "Paired"
      ],
      [
        "13:47:12",
        "BUY",
        4000000,
        6400000
      ],
      [
        "13:47:12",
        "BUY",
        4000000,
        6400000
      ],
      [
        "13:27:03",
        "BUY",
        450000,
        6000000
      ]
    ],
    "SCHW": [
      [
        "Update Time",
        "Side",
        "Imbalance",
        "Paired"
      ],
      [
        "13:47:05",
        "BUY",
        790000,
        500000
      ],
      [
        "13:47:05",
        "BUY",
        790000,
        500000
      ],
      [
        "13:26:56",
        "BUY",
        320000,
        420000
      ]
    ],
    "MA": [
      [
        "Update Time",
        "Side",
        "Imbalance",
        "Paired"
      ],
      [
        "13:47:01",
        "BUY",
        320000,
        330000
      ],
      [
        "13:47:01",
        "BUY",
        320000,
        330000
      ],
      [
        "13:26:51",
        "BUY",
        240000,
        300000
      ]
    ],
    "IBM": [
      [
        "Update Time",
        "Side",
        "Imbalance",
        "Paired"
      ],
      [
        "13:46:54",
        "BUY",
        320000,
        350000
      ],
      [
        "13:46:54",
        "BUY",
        320000,
        350000
      ],
      [
        "13:26:36",
        "BUY",
        250000,
        320000
      ]
    ],
    "NEE": [
      [
        "Update Time",
        "Side",
        "Imbalance",
        "Paired"
      ],
      [
        "13:46:41",
        "BUY",
        430000,
        470000
      ],
      [
        "13:46:41",
        "BUY",
        430000,
        470000
      ],
      [
        "13:26:17",
        "BUY",
        350000,
        450000
      ]
    ],
    "GE": [
      [
        "Update Time",
        "Side",
        "Imbalance",
        "Paired"
      ],
      [
        "13:46:25",
        "BUY",
        560000,
        480000
      ],
      [
        "13:46:25",
        "BUY",
        560000,
        480000
      ],
      [
        "13:28:26",
        "BUY",
        220000,
        450000
      ]
    ],
    "CAT": [
      [
        "Update Time",
        "Side",
        "Imbalance",
        "Paired"
      ],
      [
        "13:46:18",
        "BUY",
        60000,
        150000
      ],
      [
        "13:46:18",
        "BUY",
        60000,
        150000
      ]
    ],
    "PFE": [
      [
        "Update Time",
        "Side",
        "Imbalance",
        "Paired"
      ],
      [
        "13:45:30",
        "BUY",
        5900000,
        4600000
      ],
      [
        "13:45:30",
        "BUY",
        5900000,
        4600000
      ],
      [
        "13:29:54",
        "BUY",
        5900000,
        4600000
      ]
    ],
    "RTX": [
      [
        "Update Time",
        "Side",
        "Imbalance",
        "Paired"
      ],
      [
        "13:43:37",
        "BUY",
        260000,
        330000
      ],
      [
        "13:43:37",
        "BUY",
        260000,
        330000
      ],
      [
        "13:28:14",
        "BUY",
        380000,
        170000
      ]
    ],
    "TMO": [
      [
        "Update Time",
        "Side",
        "Imbalance",
        "Paired"
      ],
      [
        "13:43:21",
        "BUY",
        75000,
        110000
      ],
      [
        "13:43:21",
        "BUY",
        75000,
        110000
      ],
      [
        "13:29:40",
        "BUY",
        70000,
        100000
      ]
    ],
    "BMY": [
      [
        "Update Time",
        "Side",
        "Imbalance",
        "Paired"
      ],
      [
        "13:43:17",
        "BUY",
        780000,
        680000
      ],
      [
        "13:43:17",
        "BUY",
        780000,
        680000
      ],
      [
        "13:29:35",
        "BUY",
        700000,
        600000
      ]
    ],
    "USB": [
      [
        "Update Time",
        "Side",
        "Imbalance",
        "Paired"
      ],
      [
        "13:43:10",
        "BUY",
        850000,
        1100000
      ],
      [
        "13:43:10",
        "BUY",
        850000,
        1100000
      ],
      [
        "13:28:05",
        "BUY",
        800000,
        200000
      ]
    ],
    "HD": [
      [
        "Update Time",
        "Side",
        "Imbalance",
        "Paired"
      ],
      [
        "13:43:05",
        "BUY",
        100000,
        100000
      ],
      [
        "13:43:05",
        "BUY",
        100000,
        100000
      ],
      [
        "13:28:00",
        "BUY",
        50000,
        140000
      ]
    ],
    "COP": [
      [
        "Update Time",
        "Side",
        "Imbalance",
        "Paired"
      ],
      [
        "13:42:59",
        "BUY",
        1000000,
        300000
      ],
      [
        "13:42:59",
        "BUY",
        1000000,
        300000
      ],
      [
        "13:28:10",
        "BUY",
        1000000,
        200000
      ]
    ],
    "AXP": [
      [
        "Update Time",
        "Side",
        "Imbalance",
        "Paired"
      ],
      [
        "13:29:57",
        "BUY",
        150000,
        50000
      ],
      [
        "13:29:57",
        "BUY",
        150000,
        50000
      ]
    ],
    "C": [
      [
        "Update Time",
        "Side",
        "Imbalance",
        "Paired"
      ],
      [
        "13:29:48",
        "BUY",
        500000,
        500000
      ],
      [
        "13:29:48",
        "BUY",
        500000,
        500000
      ]
    ],
    "CVX": [
      [
        "Update Time",
        "Side",
        "Imbalance",
        "Paired"
      ],
      [
        "13:29:28",
        "BUY",
        750000,
        0
      ],
      [
        "13:29:28",
        "BUY",
        750000,
        0
      ]
    ],
    "T": [
      [
        "Update Time",
        "Side",
        "Imbalance",
        "Paired"
      ],
      [
        "13:29:13",
        "BUY",
        100000,
        0
      ],
      [
        "13:29:13",
        "BUY",
        100000,
        0
      ]
    ],
    "DHR": [
      [
        "Update Time",
        "Side",
        "Imbalance",
        "Paired"
      ],
      [
        "13:29:00",
        "BUY",
        270000,
        330000
      ],
      [
        "13:29:00",
        "BUY",
        270000,
        330000
      ]
    ],
    "ABBV": [
      [
        "Update Time",
        "Side",
        "Imbalance",
        "Paired"
      ],
      [
        "13:28:57",
        "BUY",
        120000,
        820000
      ],
      [
        "13:28:57",
        "BUY",
        120000,
        820000
      ]
    ],
    "UPS": [
      [
        "Update Time",
        "Side",
        "Imbalance",
        "Paired"
      ],
      [
        "13:28:53",
        "BUY",
        75000,
        350000
      ],
      [
        "13:28:53",
        "BUY",
        75000,
        350000
      ]
    ],
    "LOW": [
      [
        "Update Time",
        "Side",
        "Imbalance",
        "Paired"
      ],
      [
        "13:28:48",
        "BUY",
        100000,
        150000
      ],
      [
        "13:28:48",
        "BUY",
        100000,
        150000
      ]
    ],
    "ABT": [
      [
        "Update Time",
        "Side",
        "Imbalance",
        "Paired"
      ],
      [
        "13:28:44",
        "BUY",
        200000,
        1200000
      ],
      [
        "13:28:44",
        "BUY",
        200000,
        1200000
      ]
    ],
    "MRK": [
      [
        "Update Time",
        "Side",
        "Imbalance",
        "Paired"
      ],
      [
        "13:28:36",
        "BUY",
        250000,
        1200000
      ],
      [
        "13:28:36",
        "BUY",
        250000,
        1200000
      ]
    ],
    "PG": [
      [
        "Update Time",
        "Side",
        "Imbalance",
        "Paired"
      ],
      [
        "13:28:31",
        "BUY",
        360000,
        1000000
      ],
      [
        "13:28:31",
        "BUY",
        360000,
        1000000
      ]
    ],
    "BA": [
      [
        "Update Time",
        "Side",
        "Imbalance",
        "Paired"
      ],
      [
        "13:27:49",
        "BUY",
        200000,
        90000
      ],
      [
        "13:27:49",
        "BUY",
        200000,
        90000
      ]
    ],
    "PM": [
      [
        "Update Time",
        "Side",
        "Imbalance",
        "Paired"
      ],
      [
        "13:27:44",
        "BUY",
        200000,
        430000
      ],
      [
        "13:27:44",
        "BUY",
        200000,
        430000
      ]
    ],
    "GS": [
      [
        "Update Time",
        "Side",
        "Imbalance",
        "Paired"
      ],
      [
        "13:26:45",
        "BUY",
        80000,
        110000
      ],
      [
        "13:26:45",
        "BUY",
        80000,
        110000
      ]
    ],
    "SPGI": [
      [
        "Update Time",
        "Side",
        "Imbalance",
        "Paired"
      ],
      [
        "13:26:41",
        "BUY",
        50000,
        160000
      ],
      [
        "13:26:41",
        "BUY",
        50000,
        160000
      ]
    ],
    "PLD": [
      [
        "Update Time",
        "Side",
        "Imbalance",
        "Paired"
      ],
      [
        "13:26:08",
        "BUY",
        60000,
        370000
      ],
      [
        "13:26:08",
        "BUY",
        60000,
        370000
      ]
    ],
    "DKL": [
      [
        "Update Time",
        "Side",
        "Imbalance",
        "Paired"
      ],
      [
        "13:25:57",
        "BUY",
        70000,
        50000
      ],
      [
        "13:25:57",
        "BUY",
        70000,
        50000
      ]
    ],
    "FI": [
      [
        "Update Time",
        "Side",
        "Imbalance",
        "Paired"
      ],
      [
        "13:25:52",
        "BUY",
        200000,
        800000
      ],
      [
        "13:25:52",
        "BUY",
        200000,
        800000
      ]
    ]
  }
}