{
  "main": [
    [
      "Update Time",
      "Symbol",
      "Imbalance",
      "Paired",
      "ADV",
      "% ImbADV"
    ],
    [
      "13:34:16",
      "HD",
      50000,
      50000,
      "3760000",
      "2"
    ],
    [
      "13:34:01",
      "T",
      130000,
      130000,
      "31730000",
      "1"
    ],
    [
      "13:33:53",
      "DIS",
      170000,
      85000,
      "8189999",
      "3"
    ],
    [
      "13:33:41",
      "SCHW",
      110000,
      140000,
      "9160000",
      "2"
    ],
    [
      "13:33:32",
      "BAC",
      850000,
      560000,
      "39700000",
      "3"
    ],
    [
      "13:33:15",
      "JNJ",
      200000,
      320000,
      "8700000",
      "3"
    ],
    [
      "13:33:00",
      "UNH",
      110000,
      40000,
      "16540000",
      "1"
    ],
    [
      "13:32:54",
      "WMT",
      120000,
      110000,
      "16660000",
      "1"
    ],
    [
      "13:32:38",
      "VZ",
      1500000,
      180000,
      "18180000",
      "9"
    ],
    [
      "13:32:23",
      "NEE",
      840000,
      160000,
      "10240000",
      "9"
    ],
    [
      "13:32:11",
      "USB",
      200000,
      35000,
      "10780000",
      "2"
    ],
    [
      "13:32:00",
      "COP",
      200000,
      130000,
      "6910000",
      "3"
    ],
    [
      "13:31:53",
      "RTX",
      60000,
      75000,
      "4720000",
      "2"
    ],
    [
      "13:31:46",
      "UNP",
      120000,
      10000,
      "4440000",
      "3"
    ],
    [
      "13:31:37",
      "BMY",
      490000,
      140000,
      "12690000",
      "4"
    ],
    [
      "13:31:20",
      "ORCL",
      164000,
      300000,
      "18020000",
      "1"
    ],
    [
      "13:31:12",
      "PFE",
      281000,
      157000,
      "42600000",
      "1"
    ],
    [
      "13:31:04",
      "JPM",
      57000,
      276000,
      "8620000",
      "1"
    ],
    [
      "13:30:52",
      "PG",
      380000,
      86000,
      "7970000",
      "5"
    ],
    [
      "13:30:33",
      "WFC",
      100000,
      200000,
      "16530000",
      "1"
    ],
    [
      "13:30:26",
      "UPS",
      200000,
      35000,
      "7760000",
      "3"
    ],
    [
      "13:30:06",
      "ABBV",
      235000,
      50000,
      "5660000",
      "5"
    ],
    [
      "13:29:56",
      "PLD",
      100000,
      20000,
      "3890000",
      "3"
    ],
    [
      "13:29:50",
      "TJX",
      80000,
      230000,
      "5150000",
      "2"
    ]
  ],
  "archive": {
    "HD": [
      [
        "Update Time",
        "Side",
        "Imbalance",
        "Paired"
      ],
      [
        "13:34:16",
        "SELL",
        50000,
        50000
      ],
      [
        "13:32:16",
        "SELL",
        50000,
        50000
      ]
    ],
    "T": [
      [
        "Update Time",
        "Side",
        "Imbalance",
        "Paired"
      ],
      [
        "13:34:01",
        "SELL",
        130000,
        130000
      ]
    ],
    "DIS": [
      [
        "Update Time",
        "Side",
        "Imbalance",
        "Paired"
      ],
      [
        "13:33:53",
        "SELL",
        170000,
        85000
      ]
    ],
    "SCHW": [
      [
        "Update Time",
        "Side",
        "Imbalance",
        "Paired"
      ],
      [
        "13:33:41",
        "SELL",
        110000,
        140000
      ]
    ],
    "BAC": [
      [
        "Update Time",
        "Side",
        "Imbalance",
        "Paired"
      ],
      [
        "13:33:32",
        "SELL",
        850000,
        560000
      ]
    ],
    "JNJ": [
      [
        "Update Time",
        "Side",
        "Imbalance",
        "Paired"
      ],
      [
        "13:33:15",
        "SELL",
        200000,
        320000
      ]
    ],
    "UNH": [
      [
        "Update Time",
        "Side",
        "Imbalance",
        "Paired"
      ],
      [
        "13:33:00",
        "SELL",
        110000,
        40000
      ]
    ],
    "WMT": [
      [
        "Update Time",
        "Side",
        "Imbalance",
        "Paired"
      ],
      [
        "13:32:54",
        "SELL",
        120000,
        110000
      ]
    ],
    "VZ": [
      [
        "Update Time",
        "Side",
        "Imbalance",
        "Paired"
      ],
      [
        "13:32:38",
        "SELL",
        1500000,
        180000
      ]
    ],
    "NEE": [
      [
        "Update Time",
        "Side",
        "Imbalance",
        "Paired"
      ],
      [
        "13:32:23",
        "SELL",
        840000,
        160000
      ]
    ],
    "USB": [
      [
        "Update Time",
        "Side",
        "Imbalance",
        "Paired"
      ],
      [
        "13:32:11",
        "SELL",
        200000,
        35000
      ]
    ],
    "COP": [
      [
        "Update Time",
        "Side",
        "Imbalance",
        "Paired"
      ],
      [
        "13:32:00",
        "SELL",
        200000,
        130000
      ]
    ],
    "RTX": [
      [
        "Update Time",
        "Side",
        "Imbalance",
        "Paired"
      ],
      [
        "13:31:53",
        "SELL",
        60000,
        75000
      ]
    ],
    "UNP": [
      [
        "Update Time",
        "Side",
        "Imbalance",
        "Paired"
      ],
      [
        "13:31:46",
        "SELL",
        120000,
        10000
      ]
    ],
    "BMY": [
      [
        "Update Time",
        "Side",
        "Imbalance",
        "Paired"
      ],
      [
        "13:31:37",
        "SELL",
        490000,
        140000
      ]
    ],
    "ORCL": [
      [
        "Update Time",
        "Side",
        "Imbalance",
        "Paired"
      ],
      [
        "13:31:20",
        "SELL",
        164000,
        300000
      ]
    ],
    "PFE": [
      [
        "Update Time",
        "Side",
        "Imbalance",
        "Paired"
      ],
      [
        "13:31:12",
        "SELL",
        281000,
        157000
      ]
    ],
    "JPM": [
      [
        "Update Time",
        "Side",
        "Imbalance",
        "Paired"
      ],
      [
        "13:31:04",
        "SELL",
        57000,
        276000
      ]
    ],
    "PG": [
      [
        "Update Time",
        "Side",
        "Imbalance",
        "Paired"
      ],
      [
        "13:30:52",
        "SELL",
        380000,
        86000
      ]
    ],
    "WFC": [
      [
        "Update Time",
        "Side",
        "Imbalance",
        "Paired"
      ],
      [
        "13:30:33",
        "SELL",
        100000,
        200000
      ]
    ],
    "UPS": [
      [
        "Update Time",
        "Side",
        "Imbalance",
        "Paired"
      ],
      [
        "13:30:26",
        "SELL",
        200000,
        35000
      ]
    ],
    "ABBV": [
      [
        "Update Time",
        "Side",
        "Imbalance",
        "Paired"
      ],
      [
        "13:30:06",
        "SELL",
        235000,
        50000
      ]
    ],
    "PLD": [
      [
        "Update Time",
        "Side",
        "Imbalance",
        "Paired"
      ],
      [
        "13:29:56",
        "SELL",
        100000,
        20000
      ]
    ],
    "TJX": [
      [
        "Update Time",
        "Side",
        "Imbalance",
        "Paired"
      ],
      [
        "13:29:50",
        "SELL",
        80000,
        230000
      ]
    ]
  }
}