{
  "main": [
    [
      "Update Time",
      "Symbol",
      "Imbalance",
      "Paired",
      "ADV",
      "% ImbADV"
    ],
    [
      "13:44:03",
      "BSX",
      70000,
      40000,
      "8580000",
      "1"
    ],
    [
      "13:43:59",
      "NEE",
      60000,
      40000,
      "12900000",
      "1"
    ],
    [
      "13:43:53",
      "COP",
      50000,
      20000,
      "9420000",
      "1"
    ],
    [
      "13:38:43",
      "JPM",
      50000,
      75000,
      "11790000",
      "1"
    ],
    [
      "13:38:35",
      "UPS",
      90000,
      7000,
      "6340000",
      "2"
    ],
    [
      "13:38:30",
      "MS",
      160000,
      160000,
      "8170000",
      "2"
    ],
    [
      "13:38:18",
      "AXP",
      200000,
      10000,
      "3450000",
      "6"
    ],
    [
      "13:38:10",
      "PFE",
      130000,
      200000,
      "54020000",
      "1"
    ],
    [
      "13:37:45",
      "UBER",
      230000,
      40000,
      "20640000",
      "2"
    ],
    [
      "13:37:43",
      "WFC",
      240000,
      15000,
      "19000000",
      "2"
    ],
    [
      "13:37:32",
      "WMT",
      350000,
      50000,
      "24390000",
      "2"
    ],
    [
      "13:37:32",
      "BAC",
      180000,
      770000,
      "49660000",
      "1"
    ],
    [
      "13:37:27",
      "UNH",
      85000,
      20000,
      "12250000",
      "1"
    ],
    [
      "13:37:06",
      "V",
      110000,
      20000,
      "7130000",
      "2"
    ],
    [
      "13:36:50",
      "BMY",
      580000,
      60000,
      "14850000",
      "4"
    ],
    [
      "13:36:41",
      "GE",
      180000,
      20000,
      "5950000",
      "4"
    ],
    [
      "13:35:57",
      "DIS",
      460000,
      0,
      "11500000",
      "4"
    ]
  ],
  "archive": {
    "BSX": [
      [
        "Update Time",
        "Side",
        "Imbalance",
        "Paired"
      ],
      [
        "13:44:03",
        "SELL",
        70000,
        40000
      ],
      [
        "13:44:03",
        "SELL",
        70000,
        40000
      ],
      [
        "13:34:46",
        "SELL",
        75000,
        30000
      ]
    ],
    "NEE": [
      [
        "Update Time",
        "Side",
        "Imbalance",
        "Paired"
      ],
      [
        "13:43:59",
        "SELL",
        60000,
        40000
      ],
      [
        "13:43:59",
        "SELL",
        60000,
        40000
      ],
      [
        "13:34:56",
        "SELL",
        60000,
        40000
      ]
    ],
    "COP": [
      [
        "Update Time",
        "Side",
        "Imbalance",
        "Paired"
      ],
      [
        "13:43:53",
        "SELL",
        50000,
        20000
      ],
      [
        "13:43:53",
        "SELL",
        50000,
        20000
      ],
      [
        "13:36:12",
        "SELL",
        60000,
        10000
      ]
    ],
    "JPM": [
      [
        "Update Time",
        "Side",
        "Imbalance",
        "Paired"
      ],
      [
        "13:38:43",
        "SELL",
        50000,
        75000
      ],
      [
        "13:38:43",
        "SELL",
        50000,
        75000
      ]
    ],
    "UPS": [
      [
        "Update Time",
        "Side",
        "Imbalance",
        "Paired"
      ],
      [
        "13:38:35",
        "SELL",
        90000,
        7000
      ],
      [
        "13:38:35",
        "SELL",
        90000,
        7000
      ]
    ],
    "MS": [
      [
        "Update Time",
        "Side",
        "Imbalance",
        "Paired"
      ],
      [
        "13:38:30",
        "SELL",
        160000,
        160000
      ],
      [
        "13:38:30",
        "SELL",
        160000,
        160000
      ]
    ],
    "AXP": [
      [
        "Update Time",
        "Side",
        "Imbalance",
        "Paired"
      ],
      [
        "13:38:18",
        "SELL",
        200000,
        10000
      ],
      [
        "13:38:18",
        "SELL",
        200000,
        10000
      ]
    ],
    "PFE": [
      [
        "Update Time",
        "Side",
        "Imbalance",
        "Paired"
      ],
      [
        "13:38:10",
        "SELL",
        130000,
        200000
      ],
      [
        "13:38:10",
        "SELL",
        130000,
        200000
      ]
    ],
    "UBER": [
      [
        "Update Time",
        "Side",
        "Imbalance",
        "Paired"
      ],
      [
        "13:37:45",
        "SELL",
        230000,
        40000
      ],
      [
        "13:37:45",
        "SELL",
        230000,
        40000
      ]
    ],
    "WFC": [
      [
        "Update Time",
        "Side",
        "Imbalance",
        "Paired"
      ],
      [
        "13:37:43",
        "SELL",
        240000,
        15000
      ],
      [
        "13:37:43",
        "SELL",
        240000,
        15000
      ]
    ],
    "WMT": [
      [
        "Update Time",
        "Side",
        "Imbalance",
        "Paired"
      ],
      [
        "13:37:32",
        "SELL",
        350000,
        50000
      ],
      [
        "13:37:32",
        "SELL",
        350000,
        50000
      ]
    ],
    "BAC": [
      [
        "Update Time",
        "Side",
        "Imbalance",
        "Paired"
      ],
      [
        "13:37:32",
        "SELL",
        180000,
        770000
      ],
      [
        "13:37:32",
        "SELL",
        180000,
        770000
      ]
    ],
    "UNH": [
      [
        "Update Time",
        "Side",
        "Imbalance",
        "Paired"
      ],
      [
        "13:37:27",
        "SELL",
        85000,
        20000
      ],
      [
        "13:37:27",
        "SELL",
        85000,
        20000
      ]
    ],
    "V": [
      [
        "Update Time",
        "Side",
        "Imbalance",
        "Paired"
      ],
      [
        "13:37:06",
        "SELL",
        110000,
        20000
      ],
      [
        "13:37:06",
        "SELL",
        110000,
        20000
      ]
    ],
    "BMY": [
      [
        "Update Time",
        "Side",
        "Imbalance",
        "Paired"
      ],
      [
        "13:36:50",
        "SELL",
        580000,
        60000
      ],
      [
        "13:36:50",
        "SELL",
        580000,
        60000
      ]
    ],
    "GE": [
      [
        "Update Time",
        "Side",
        "Imbalance",
        "Paired"
      ],
      [
        "13:36:41",
        "SELL",
        180000,
        20000
      ],
      [
        "13:36:41",
        "SELL",
        180000,
        20000
      ]
    ],
    "DIS": [
      [
        "Update Time",
        "Side",
        "Imbalance",
        "Paired"
      ],
      [
        "13:35:57",
        "SELL",
        460000,
        0
      ],
      [
        "13:35:57",
        "SELL",
        460000,
        0
      ]
    ]
  }
}