{
  "main": [
    [
      "Update Time",
      "Symbol",
      "Imbalance",
      "Paired",
      "ADV",
      "% ImbADV"
    ],
    [
      "13:33:23",
      "CAT",
      100000,
      50000,
      "2900000",
      "4"
    ],
    [
      "13:33:17",
      "ACN",
      120000,
      320000,
      "4450000",
      "3"
    ],
    [
      "13:33:07",
      "UBER",
      150000,
      180000,
      "18600000",
      "1"
    ],
    [
      "13:32:59",
      "BAC",
      220000,
      320000,
      "39700000",
      "1"
    ],
    [
      "13:32:51",
      "IBM",
      220000,
      250000,
      "4820000",
      "5"
    ],
    [
      "13:32:43",
      "V",
      1300000,
      70000,
      "6300000",
      "21"
    ],
    [
      "13:32:28",
      "PM",
      440000,
      510000,
      "5830000",
      "8"
    ],
    [
      "13:32:21",
      "WMT",
      790000,
      180000,
      "16660000",
      "5"
    ],
    [
      "13:31:57",
      "KO",
      210000,
      610000,
      "16550000",
      "2"
    ],
    [
      "13:31:50",
      "JNJ",
      180000,
      100000,
      "8700000",
      "3"
    ],
    [
      "13:31:41",
      "SPGI",
      50000,
      250000,
      "1240000",
      "5"
    ],
    [
      "13:31:09",
      "XOM",
      600000,
      300000,
      "16180000",
      "4"
    ],
    [
      "13:30:54",
      "LOW",
      76000,
      35000,
      "2840000",
      "3"
    ],
    [
      "13:30:44",
      "ABT",
      510000,
      110000,
      "6490000",
      "8"
    ],
    [
      "13:30:37",
      "ABBV",
      140000,
      970000,
      "5660000",
      "3"
    ],
    [
      "13:30:23",
      "WFC",
      220000,
      140000,
      "16530000",
      "2"
    ],
    [
      "13:30:10",
      "PG",
      400000,
      200000,
      "7970000",
      "6"
    ],
    [
      "13:30:04",
      "JPM",
      69000,
      660000,
      "8620000",
      "1"
    ],
    [
      "13:29:49",
      "FI",
      100000,
      40000,
      "5020000",
      "2"
    ]
  ],
  "archive": {
    "CAT": [
      [
        "Update Time",
        "Side",
        "Imbalance",
        "Paired"
      ],
      [
        "13:33:23",
        "SELL",
        100000,
        50000
      ]
    ],
    "ACN": [
      [
        "Update Time",
        "Side",
        "Imbalance",
        "Paired"
      ],
      [
        "13:33:17",
        "SELL",
        120000,
        320000
      ]
    ],
    "UBER": [
      [
        "Update Time",
        "Side",
        "Imbalance",
        "Paired"
      ],
      [
        "13:33:07",
        "SELL",
        150000,
        180000
      ]
    ],
    "BAC": [
      [
        "Update Time",
        "Side",
        "Imbalance",
        "Paired"
      ],
      [
        "13:32:59",
        "SELL",
        220000,
        320000
      ]
    ],
    "IBM": [
      [
        "Update Time",
        "Side",
        "Imbalance",
        "Paired"
      ],
      [
        "13:32:51",
        "SELL",
        220000,
        250000
      ]
    ],
    "V": [
      [
        "Update Time",
        "Side",
        "Imbalance",
        "Paired"
      ],
      [
        "13:32:43",
        "SELL",
        1300000,
        70000
      ]
    ],
    "PM": [
      [
        "Update Time",
        "Side",
        "Imbalance",
        "Paired"
      ],
      [
        "13:32:28",
        "SELL",
        440000,
        510000
      ]
    ],
    "WMT": [
      [
        "Update Time",
        "Side",
        "Imbalance",
        "Paired"
      ],
      [
        "13:32:21",
        "SELL",
        790000,
        180000
      ]
    ],
    "KO": [
      [
        "Update Time",
        "Side",
        "Imbalance",
        "Paired"
      ],
      [
        "13:31:57",
        "SELL",
        210000,
        610000
      ]
    ],
    "JNJ": [
      [
        "Update Time",
        "Side",
        "Imbalance",
        "Paired"
      ],
      [
        "13:31:50",
        "SELL",
        180000,
        100000
      ]
    ],
    "SPGI": [
      [
        "Update Time",
        "Side",
        "Imbalance",
        "Paired"
      ],
      [
        "13:31:41",
        "SELL",
        50000,
        250000
      ]
    ],
    "XOM": [
      [
        "Update Time",
        "Side",
        "Imbalance",
        "Paired"
      ],
      [
        "13:31:09",
        "SELL",
        600000,
        300000
      ]
    ],
    "LOW": [
      [
        "Update Time",
        "Side",
        "Imbalance",
        "Paired"
      ],
      [
        "13:30:54",
        "SELL",
        76000,
        35000
      ]
    ],
    "ABT": [
      [
        "Update Time",
        "Side",
        "Imbalance",
        "Paired"
      ],
      [
        "13:30:44",
        "SELL",
        510000,
        110000
      ]
    ],
    "ABBV": [
      [
        "Update Time",
        "Side",
        "Imbalance",
        "Paired"
      ],
      [
        "13:30:37",
        "SELL",
        140000,
        970000
      ]
    ],
    "WFC": [
      [
        "Update Time",
        "Side",
        "Imbalance",
        "Paired"
      ],
      [
        "13:30:23",
        "SELL",
        220000,
        140000
      ]
    ],
    "PG": [
      [
        "Update Time",
        "Side",
        "Imbalance",
        "Paired"
      ],
      [
        "13:30:10",
        "SELL",
        400000,
        200000
      ]
    ],
    "JPM": [
      [
        "Update Time",
        "Side",
        "Imbalance",
        "Paired"
      ],
      [
        "13:30:04",
        "SELL",
        69000,
        660000
      ]
    ],
    "FI": [
      [
        "Update Time",
        "Side",
        "Imbalance",
        "Paired"
      ],
      [
        "13:29:49",
        "SELL",
        100000,
        40000
      ]
    ]
  }
}