{
  "main": [
    [
      "Update Time",
      "Symbol",
      "Imbalance",
      "Paired",
      "ADV",
      "% ImbADV"
    ],
    [
      "13:46:07",
      "XOM",
      530000,
      130000,
      "17370000",
      "4"
    ],
    [
      "13:42:26",
      "UNH",
      60000,
      70000,
      "6300000",
      "1"
    ],
    [
      "13:41:13",
      "COP",
      250000,
      60000,
      "9390000",
      "3"
    ],
    [
      "13:30:33",
      "CVX",
      600000,
      50000,
      "9280000",
      "7"
    ],
    [
      "13:30:26",
      "DIS",
      200000,
      200000,
      "10670000",
      "2"
    ],
    [
      "13:29:48",
      "BRK.B",
      55000,
      140000,
      "0",
      "0"
    ],
    [
      "13:29:35",
      "WFC",
      210000,
      170000,
      "18960000",
      "2"
    ],
    [
      "13:29:31",
      "JPM",
      50000,
      100000,
      "11580000",
      "1"
    ],
    [
      "13:29:23",
      "DHR",
      60000,
      40000,
      "4740000",
      "2"
    ],
    [
      "13:29:14",
      "UPS",
      200000,
      30000,
      "6410000",
      "4"
    ],
    [
      "13:29:03",
      "MRK",
      450000,
      360000,
      "18140000",
      "3"
    ],
    [
      "13:27:47",
      "IBM",
      50000,
      40000,
      "5160000",
      "1"
    ]
  ],
  "archive": {
    "XOM": [
      [
        "Update Time",
        "Side",
        "Imbalance",
        "Paired"
      ],
      [
        "13:46:07",
        "SELL",
        530000,
        130000
      ],
      [
        "13:46:07",
        "SELL",
        530000,
        130000
      ],
      [
        "13:30:17",
        "SELL",
        500000,
        100000
      ]
    ],
    "UNH": [
      [
        "Update Time",
        "Side",
        "Imbalance",
        "Paired"
      ],
      [
        "13:42:26",
        "SELL",
        60000,
        70000
      ],
      [
        "13:42:26",
        "SELL",
        60000,
        70000
      ],
      [
        "13:28:25",
        "SELL",
        70000,
        60000
      ]
    ],
    "COP": [
      [
        "Update Time",
        "Side",
        "Imbalance",
        "Paired"
      ],
      [
        "13:41:13",
        "SELL",
        250000,
        60000
      ],
      [
        "13:41:13",
        "SELL",
        250000,
        60000
      ],
      [
        "13:30:53",
        "SELL",
        250000,
        60000
      ]
    ],
    "CVX": [
      [
        "Update Time",
        "Side",
        "Imbalance",
        "Paired"
      ],
      [
        "13:30:33",
        "SELL",
        600000,
        50000
      ],
      [
        "13:30:33",
        "SELL",
        600000,
        50000
      ]
    ],
    "DIS": [
      [
        "Update Time",
        "Side",
        "Imbalance",
        "Paired"
      ],
      [
        "13:30:26",
        "SELL",
        200000,
        200000
      ],
      [
        "13:30:26",
        "SELL",
        200000,
        200000
      ]
    ],
    "BRK.B": [
      [
        "Update Time",
        "Side",
        "Imbalance",
        "Paired"
      ],
      [
        "13:29:48",
        "SELL",
        55000,
        140000
      ],
      [
        "13:29:48",
        "SELL",
        55000,
        140000
      ]
    ],
    "WFC": [
      [
        "Update Time",
        "Side",
        "Imbalance",
        "Paired"
      ],
      [
        "13:29:35",
        "SELL",
        210000,
        170000
      ],
      [
        "13:29:35",
        "SELL",
        210000,
        170000
      ]
    ],
    "JPM": [
      [
        "Update Time",
        "Side",
        "Imbalance",
        "Paired"
      ],
      [
        "13:29:31",
        "SELL",
        50000,
        100000
      ],
      [
        "13:29:31",
        "SELL",
        50000,
        100000
      ]
    ],
    "DHR": [
      [
        "Update Time",
        "Side",
        "Imbalance",
        "Paired"
      ],
      [
        "13:29:23",
        "SELL",
        60000,
        40000
      ],
      [
        "13:29:23",
        "SELL",
        60000,
        40000
      ]
    ],
    "UPS": [
      [
        "Update Time",
        "Side",
        "Imbalance",
        "Paired"
      ],
      [
        "13:29:14",
        "SELL",
        200000,
        30000
      ],
      [
        "13:29:14",
        "SELL",
        200000,
        30000
      ]
    ],
    "MRK": [
      [
        "Update Time",
        "Side",
        "Imbalance",
        "Paired"
      ],
      [
        "13:29:03",
        "SELL",
        450000,
        360000
      ],
      [
        "13:29:03",
        "SELL",
        450000,
        360000
      ]
    ],
    "IBM": [
      [
        "Update Time",
        "Side",
        "Imbalance",
        "Paired"
      ],
      [
        "13:27:47",
        "SELL",
        50000,
        40000
      ],
      [
        "13:27:47",
        "SELL",
        50000,
        40000
      ]
    ]
  }
}