{
  "main": [
    [
      "Update Time",
      "Symbol",
      "Imbalance",
      "Paired",
      "ADV",
      "% ImbADV"
    ],
    [
      "13:31:14",
      "USB",
      150000,
      150000,
      "9360000",
      "2"
    ],
    [
      "13:30:52",
      "BMY",
      90000,
      90000,
      "14180000",
      "1"
    ],
    [
      "13:30:44",
      "UNP",
      80000,
      280000,
      "4530000",
      "2"
    ],
    [
      "13:30:32",
      "COP",
      50000,
      500000,
      "6640000",
      "1"
    ],
    [
      "13:30:19",
      "BSX",
      110000,
      50000,
      "8600000",
      "2"
    ]
  ],
  "archive": {
    "USB": [
      [
        "Update Time",
        "Side",
        "Imbalance",
        "Paired"
      ],
      [
        "13:31:14",
        "SELL",
        150000,
        150000
      ]
    ],
    "BMY": [
      [
        "Update Time",
        "Side",
        "Imbalance",
        "Paired"
      ],
      [
        "13:30:52",
        "SELL",
        90000,
        90000
      ]
    ],
    "UNP": [
      [
        "Update Time",
        "Side",
        "Imbalance",
        "Paired"
      ],
      [
        "13:30:44",
        "SELL",
        80000,
        280000
      ]
    ],
    "COP": [
      [
        "Update Time",
        "Side",
        "Imbalance",
        "Paired"
      ],
      [
        "13:30:32",
        "SELL",
        50000,
        500000
      ]
    ],
    "BSX": [
      [
        "Update Time",
        "Side",
        "Imbalance",
        "Paired"
      ],
      [
        "13:30:19",
        "SELL",
        110000,
        50000
      ]
    ]
  }
}